<?xml version="1.0" encoding="UTF-8"?>

<mt_enum_config>
  <enum_spaces>
    <enum_space name="metratech.com/ancillarycharges">
      <description>Ancillary Charges EnumType</description>
      <enums>
        <enum name="ChargeType">
          <description>Ancillary Charge Type</description>
          <entries>
            <entry name="402A">
              <value>402A</value>
            </entry>
            <entry name="402B">
              <value>402B</value>
            </entry>
            <entry name="409">
              <value>409</value>
            </entry>
            <entry name="409A">
              <value>409A</value>
            </entry>
            <entry name="ACCTFEE-BT">
              <value>ACCTFEE-BT</value>
            </entry>
            <entry name="ACCTFEE-PDF">
              <value>ACCTFEE-PDF</value>
            </entry>
            <entry name="AP-CD">
              <value>AP-CD</value>
            </entry>
            <entry name="AP-CDSPLIT">
              <value>AP-CDSPLIT</value>
            </entry>
            <entry name="AP-EDIT">
              <value>AP-EDIT</value>
            </entry>
            <entry name="AP-FILE">
              <value>AP-FILE</value>
            </entry>
            <entry name="AP-MISC">
              <value>AP-MISC</value>
            </entry>
            <entry name="AP-RUSH">
              <value>AP-RUSH</value>
            </entry>
            <entry name="AP-RUSH1">
              <value>AP-RUSH1</value>
            </entry>
            <entry name="AP-RUSH2">
              <value>AP-RUSH2</value>
            </entry>
            <entry name="BM-EADD">
              <value>BM-EADD</value>
            </entry>
            <entry name="BM-EFOD">
              <value>BM-EFOD</value>
            </entry>
            <entry name="BM-EFODINTL">
              <value>BM-EFODINTL</value>
            </entry>
            <entry name="BM-EMAIL">
              <value>BM-EMAIL</value>
            </entry>
            <entry name="BM-FAX">
              <value>BM-FAX</value>
            </entry>
            <entry name="BM-FAXINTL">
              <value>BM-FAXINTL</value>
            </entry>
            <entry name="BM-FOD">
              <value>BM-FOD</value>
            </entry>
            <entry name="BM-FODINTL">
              <value>BM-FODINTL</value>
            </entry>
            <entry name="BM-MISC">
              <value>BM-MISC</value>
            </entry>
            <entry name="BM-RUSH">
              <value>BM-RUSH</value>
            </entry>
            <entry name="BM-VMAIL">
              <value>BM-VMAIL</value>
            </entry>
            <entry name="C050">
              <value>C050</value>
            </entry>
            <entry name="C100">
              <value>C100</value>
            </entry>
            <entry name="C125">
              <value>C125</value>
            </entry>
            <entry name="C175">
              <value>C175</value>
            </entry>
            <entry name="C200">
              <value>C200</value>
            </entry>
            <entry name="C-AFTERHRS">
              <value>C-AFTERHRS</value>
            </entry>
            <entry name="CD-BILLING">
              <value>CD-BILLING</value>
            </entry>
            <entry name="CMOD">
              <value>CMOD</value>
            </entry>
            <entry name="COMB-MINUIFN">
              <value>COMB-MINUIFN</value>
            </entry>
            <entry name="COMM">
              <value>COMM</value>
            </entry>
            <entry name="COMM1">
              <value>COMM1</value>
            </entry>
            <entry name="COMMADDL">
              <value>COMMADDL</value>
            </entry>
            <entry name="COVERLETTE">
              <value>COVERLETTE</value>
            </entry>
            <entry name="CPACK">
              <value>CPACK</value>
            </entry>
            <entry name="CUSTMUSIC">
              <value>CUSTMUSIC</value>
            </entry>
            <entry name="C-VCCONFLDR">
              <value>C-VCCONFLDR</value>
            </entry>
            <entry name="DAT">
              <value>DAT</value>
            </entry>
            <entry name="DEDICATED">
              <value>DEDICATED</value>
            </entry>
            <entry name="DEVEL-IS">
              <value>DEVEL-IS</value>
            </entry>
            <entry name="DEVEL-RD">
              <value>DEVEL-RD</value>
            </entry>
            <entry name="DIALOUT">
              <value>DIALOUT</value>
            </entry>
            <entry name="DISC-FRAUD">
              <value>DISC-FRAUD</value>
            </entry>
            <entry name="DISC-FULFILLMENT">
              <value>DISC-FULFILLMENT</value>
            </entry>
            <entry name="DISC-OP">
              <value>DISC-OP</value>
            </entry>
            <entry name="DISC-OPNDRS">
              <value>DISC-OPNDRS</value>
            </entry>
            <entry name="DISC-READY">
              <value>DISC-READY</value>
            </entry>
            <entry name="DISC-RES">
              <value>DISC-RES</value>
            </entry>
            <entry name="DISC-SALES">
              <value>DISC-SALES</value>
            </entry>
            <entry name="DISC-SOUND">
              <value>DISC-SOUND</value>
            </entry>
            <entry name="DISK">
              <value>DISK</value>
            </entry>
            <entry name="EC-ADDL90">
              <value>EC-ADDL90</value>
            </entry>
            <entry name="EC-APP">
              <value>EC-APP</value>
            </entry>
            <entry name="EC-ASEAT">
              <value>EC-ASEAT</value>
            </entry>
            <entry name="EC-AUD">
              <value>EC-AUD</value>
            </entry>
            <entry name="EC-AUDVID">
              <value>EC-AUDVID</value>
            </entry>
            <entry name="EC-AVSEAT">
              <value>EC-AVSEAT</value>
            </entry>
            <entry name="EC-BRAND">
              <value>EC-BRAND</value>
            </entry>
            <entry name="EC-FILE">
              <value>EC-FILE</value>
            </entry>
            <entry name="EC-OVER">
              <value>EC-OVER</value>
            </entry>
            <entry name="EC-REC">
              <value>EC-REC</value>
            </entry>
            <entry name="EC-REPLAY">
              <value>EC-REPLAY</value>
            </entry>
            <entry name="EC-RMSU">
              <value>EC-RMSU</value>
            </entry>
            <entry name="EC-RMU">
              <value>EC-RMU</value>
            </entry>
            <entry name="EC-SEATSU">
              <value>EC-SEATSU</value>
            </entry>
            <entry name="EC-WEB">
              <value>EC-WEB</value>
            </entry>
            <entry name="EC-WSEAT">
              <value>EC-WSEAT</value>
            </entry>
            <entry name="EH-EFT">
              <value>EH-EFT</value>
            </entry>
            <entry name="EH-FILCON">
              <value>EH-FILCON</value>
            </entry>
            <entry name="EH-FILCONRS">
              <value>EH-FILCONRS</value>
            </entry>
            <entry name="EH-PROG">
              <value>EH-PROG</value>
            </entry>
            <entry name="EH-WRSVPCH">
              <value>EH-WRSVPCH</value>
            </entry>
            <entry name="EH-WRSVPSP">
              <value>EH-WRSVPSP</value>
            </entry>
            <entry name="EQ-PHONERENT">
              <value>EQ-PHONERENT</value>
            </entry>
            <entry name="EQ-RENT">
              <value>EQ-RENT</value>
            </entry>
            <entry name="EQ-SALE">
              <value>EQ-SALE</value>
            </entry>
            <entry name="EREM">
              <value>EREM</value>
            </entry>
            <entry name="EVENTFEE">
              <value>EVENTFEE</value>
            </entry>
            <entry name="FAX">
              <value>FAX</value>
            </entry>
            <entry name="FAXINTL">
              <value>FAXINTL</value>
            </entry>
            <entry name="FL-2DAYSHIP">
              <value>FL-2DAYSHIP</value>
            </entry>
            <entry name="FL-ARCHIVE">
              <value>FL-ARCHIVE</value>
            </entry>
            <entry name="FL-ASSEMBLE">
              <value>FL-ASSEMBLE</value>
            </entry>
            <entry name="FL-BLKSHP">
              <value>FL-BLKSHP</value>
            </entry>
            <entry name="FL-CD1">
              <value>FL-CD1</value>
            </entry>
            <entry name="FL-CD2">
              <value>FL-CD2</value>
            </entry>
            <entry name="FL-CD3">
              <value>FL-CD3</value>
            </entry>
            <entry name="FL-CD4">
              <value>FL-CD4</value>
            </entry>
            <entry name="FL-COPY">
              <value>FL-COPY</value>
            </entry>
            <entry name="FL-COPYC">
              <value>FL-COPYC</value>
            </entry>
            <entry name="FL-CS">
              <value>FL-CS</value>
            </entry>
            <entry name="FL-CSTFUL">
              <value>FL-CSTFUL</value>
            </entry>
            <entry name="FL-CWCRD">
              <value>FL-CWCRD</value>
            </entry>
            <entry name="FL-CWLTR">
              <value>FL-CWLTR</value>
            </entry>
            <entry name="FL-FAX">
              <value>FL-FAX</value>
            </entry>
            <entry name="FL-FAXINTL">
              <value>FL-FAXINTL</value>
            </entry>
            <entry name="FL-FLC">
              <value>FL-FLC</value>
            </entry>
            <entry name="FL-HANDLE">
              <value>FL-HANDLE</value>
            </entry>
            <entry name="FL-MISC">
              <value>FL-MISC</value>
            </entry>
            <entry name="FL-PACKET">
              <value>FL-PACKET</value>
            </entry>
            <entry name="FL-PRINT">
              <value>FL-PRINT</value>
            </entry>
            <entry name="FL-RUSH">
              <value>FL-RUSH</value>
            </entry>
            <entry name="FL-SHIP">
              <value>FL-SHIP</value>
            </entry>
            <entry name="FL-STORAGE">
              <value>FL-STORAGE</value>
            </entry>
            <entry name="FL-TAPE1">
              <value>FL-TAPE1</value>
            </entry>
            <entry name="FL-TAPE2">
              <value>FL-TAPE2</value>
            </entry>
            <entry name="FL-TAPE3">
              <value>FL-TAPE3</value>
            </entry>
            <entry name="FL-TAPE4">
              <value>FL-TAPE4</value>
            </entry>
            <entry name="FL-WCBSU">
              <value>FL-WCBSU</value>
            </entry>
            <entry name="FL-WCLC">
              <value>FL-WCLC</value>
            </entry>
            <entry name="FL-WLPKT">
              <value>FL-WLPKT</value>
            </entry>
            <entry name="FL-WPC">
              <value>FL-WPC</value>
            </entry>
            <entry name="HOSTCNTL">
              <value>HOSTCNTL</value>
            </entry>
            <entry name="INTECH-A">
              <value>INTECH-A</value>
            </entry>
            <entry name="INVITE">
              <value>INVITE</value>
            </entry>
            <entry name="MISC">
              <value>MISC</value>
            </entry>
            <entry name="MSG">
              <value>MSG</value>
            </entry>
            <entry name="MSGI">
              <value>MSGI</value>
            </entry>
            <entry name="NOTIF">
              <value>NOTIF</value>
            </entry>
            <entry name="PLIST3">
              <value>PLIST3</value>
            </entry>
            <entry name="PLIST4">
              <value>PLIST4</value>
            </entry>
            <entry name="PLIST5">
              <value>PLIST5</value>
            </entry>
            <entry name="PLIST6">
              <value>PLIST6</value>
            </entry>
            <entry name="PLIST7">
              <value>PLIST7</value>
            </entry>
            <entry name="PLIST8">
              <value>PLIST8</value>
            </entry>
            <entry name="PM-GTP">
              <value>PM-GTP</value>
            </entry>
            <entry name="PM-GTS">
              <value>PM-GTS</value>
            </entry>
            <entry name="PM-PSS">
              <value>PM-PSS</value>
            </entry>
            <entry name="POLLING">
              <value>POLLING</value>
            </entry>
            <entry name="RCREHER">
              <value>RCREHER</value>
            </entry>
            <entry name="RC-SEATA">
              <value>RC-SEATA</value>
            </entry>
            <entry name="RC-SEATB">
              <value>RC-SEATB</value>
            </entry>
            <entry name="RC-SEATBRND">
              <value>RC-SEATBRND</value>
            </entry>
            <entry name="RC-SEATOVER">
              <value>RC-SEATOVER</value>
            </entry>
            <entry name="RC-SEATSET">
              <value>RC-SEATSET</value>
            </entry>
            <entry name="RC-SEATSSL">
              <value>RC-SEATSSL</value>
            </entry>
            <entry name="RC-SSLSU">
              <value>RC-SSLSU</value>
            </entry>
            <entry name="RECR-SETUP">
              <value>RECR-SETUP</value>
            </entry>
            <entry name="RECRUIT">
              <value>RECRUIT</value>
            </entry>
            <entry name="REMCAN">
              <value>REMCAN</value>
            </entry>
            <entry name="REMINDER">
              <value>REMINDER</value>
            </entry>
            <entry name="REM-SETUP">
              <value>REM-SETUP</value>
            </entry>
            <entry name="REP-CONDAT">
              <value>REP-CONDAT</value>
            </entry>
            <entry name="REP-FUTRES">
              <value>REP-FUTRES</value>
            </entry>
            <entry name="REPLAY">
              <value>REPLAY</value>
            </entry>
            <entry name="REPLAY2">
              <value>REPLAY2</value>
            </entry>
            <entry name="REP-OCS">
              <value>REP-OCS</value>
            </entry>
            <entry name="REP-OOPS">
              <value>REP-OOPS</value>
            </entry>
            <entry name="REP-ORES">
              <value>REP-ORES</value>
            </entry>
            <entry name="REPORT">
              <value>REPORT</value>
            </entry>
            <entry name="REP-POLL">
              <value>REP-POLL</value>
            </entry>
            <entry name="REP-PSTCON">
              <value>REP-PSTCON</value>
            </entry>
            <entry name="REP-RSVP">
              <value>REP-RSVP</value>
            </entry>
            <entry name="REP-SCAST">
              <value>REP-SCAST</value>
            </entry>
            <entry name="REP-VCAST">
              <value>REP-VCAST</value>
            </entry>
            <entry name="RPLACE">
              <value>RPLACE</value>
            </entry>
            <entry name="RSVP">
              <value>RSVP</value>
            </entry>
            <entry name="RSVP-CWSETUP">
              <value>RSVP-CWSETUP</value>
            </entry>
            <entry name="RSVP-EWSETUP">
              <value>RSVP-EWSETUP</value>
            </entry>
            <entry name="RSVP-FH">
              <value>RSVP-FH</value>
            </entry>
            <entry name="RSVPLARGE">
              <value>RSVPLARGE</value>
            </entry>
            <entry name="RSVPMED">
              <value>RSVPMED</value>
            </entry>
            <entry name="RSVP-PH">
              <value>RSVP-PH</value>
            </entry>
            <entry name="RSVP-PSETUP">
              <value>RSVP-PSETUP</value>
            </entry>
            <entry name="RSVPREKEY">
              <value>RSVPREKEY</value>
            </entry>
            <entry name="RSVP-RTREP">
              <value>RSVP-RTREP</value>
            </entry>
            <entry name="RSVPWEB">
              <value>RSVPWEB</value>
            </entry>
            <entry name="RSVPWEBE">
              <value>RSVPWEBE</value>
            </entry>
            <entry name="RSVP-WSETUP">
              <value>RSVP-WSETUP</value>
            </entry>
            <entry name="SB-BASIC">
              <value>SB-BASIC</value>
            </entry>
            <entry name="SB-BSETUP">
              <value>SB-BSETUP</value>
            </entry>
            <entry name="SB-CUSTOM">
              <value>SB-CUSTOM</value>
            </entry>
            <entry name="SB-DELUXE">
              <value>SB-DELUXE</value>
            </entry>
            <entry name="SB-EFOD">
              <value>SB-EFOD</value>
            </entry>
            <entry name="SB-EFODINTL">
              <value>SB-EFODINTL</value>
            </entry>
            <entry name="SB-INTLDAY">
              <value>SB-INTLDAY</value>
            </entry>
            <entry name="SB-MIN8">
              <value>SB-MIN8</value>
            </entry>
            <entry name="SB-MIND">
              <value>SB-MIND</value>
            </entry>
            <entry name="SB-MISC">
              <value>SB-MISC</value>
            </entry>
            <entry name="SB-REPORTA">
              <value>SB-REPORTA</value>
            </entry>
            <entry name="SB-REPORTR">
              <value>SB-REPORTR</value>
            </entry>
            <entry name="SB-RUSH">
              <value>SB-RUSH</value>
            </entry>
            <entry name="SB-SETUP">
              <value>SB-SETUP</value>
            </entry>
            <entry name="SB-SETUPAD">
              <value>SB-SETUPAD</value>
            </entry>
            <entry name="SB-SPECIAL">
              <value>SB-SPECIAL</value>
            </entry>
            <entry name="SB-TRANENT">
              <value>SB-TRANENT</value>
            </entry>
            <entry name="SB-TRANSCR">
              <value>SB-TRANSCR</value>
            </entry>
            <entry name="SB-UPLOAD">
              <value>SB-UPLOAD</value>
            </entry>
            <entry name="SB-VCSETUP">
              <value>SB-VCSETUP</value>
            </entry>
            <entry name="SC-ADDPARTIC">
              <value>SC-ADDPARTIC</value>
            </entry>
            <entry name="SC-ADDREPLAY">
              <value>SC-ADDREPLAY</value>
            </entry>
            <entry name="SC-HUGE">
              <value>SC-HUGE</value>
            </entry>
            <entry name="SC-LARGE">
              <value>SC-LARGE</value>
            </entry>
            <entry name="SC-MEDIUM">
              <value>SC-MEDIUM</value>
            </entry>
            <entry name="SC-SMALL">
              <value>SC-SMALL</value>
            </entry>
            <entry name="SC-VERYLARGE">
              <value>SC-VERYLARGE</value>
            </entry>
            <entry name="SETUP-FEE">
              <value>SETUP-FEE</value>
            </entry>
            <entry name="SHIPPRTYL">
              <value>SHIPPRTYL</value>
            </entry>
            <entry name="SHIPPRTYP">
              <value>SHIPPRTYP</value>
            </entry>
            <entry name="SHIPSTDL">
              <value>SHIPSTDL</value>
            </entry>
            <entry name="SHIPSTDP">
              <value>SHIPSTDP</value>
            </entry>
            <entry name="TRAN2">
              <value>TRAN2</value>
            </entry>
            <entry name="TRAN3">
              <value>TRAN3</value>
            </entry>
            <entry name="TRANASAP">
              <value>TRANASAP</value>
            </entry>
            <entry name="TRANLSCRP">
              <value>TRANLSCRP</value>
            </entry>
            <entry name="TRANSLATE">
              <value>TRANSLATE</value>
            </entry>
            <entry name="VC-ADD90">
              <value>VC-ADD90</value>
            </entry>
            <entry name="VC-FILE">
              <value>VC-FILE</value>
            </entry>
            <entry name="VC-MADD90">
              <value>VC-MADD90</value>
            </entry>
            <entry name="VC-MREC">
              <value>VC-MREC</value>
            </entry>
            <entry name="VC-MRPLY">
              <value>VC-MRPLY</value>
            </entry>
            <entry name="VCRC-TRAIN">
              <value>VCRC-TRAIN</value>
            </entry>
            <entry name="VC-REC">
              <value>VC-REC</value>
            </entry>
            <entry name="VC-REG">
              <value>VC-REG</value>
            </entry>
            <entry name="VC-RO">
              <value>VC-RO</value>
            </entry>
            <entry name="VC-RPLY">
              <value>VC-RPLY</value>
            </entry>
            <entry name="VC-SEATA">
              <value>VC-SEATA</value>
            </entry>
            <entry name="VC-SEATASL">
              <value>VC-SEATASL</value>
            </entry>
            <entry name="VC-SEATB">
              <value>VC-SEATB</value>
            </entry>
            <entry name="VC-SEATBREC">
              <value>VC-SEATBREC</value>
            </entry>
            <entry name="VC-SEATBRND">
              <value>VC-SEATBRND</value>
            </entry>
            <entry name="VC-SEATOVER">
              <value>VC-SEATOVER</value>
            </entry>
            <entry name="VC-SEATSET">
              <value>VC-SEATSET</value>
            </entry>
            <entry name="VC-SEATSTRG">
              <value>VC-SEATSTRG</value>
            </entry>
            <entry name="VC-SSL">
              <value>VC-SSL</value>
            </entry>
            <entry name="WC-CON">
              <value>WC-CON</value>
            </entry>
            <entry name="WC-MIN">
              <value>WC-MIN</value>
            </entry>
            <entry name="WC-MIN8">
              <value>WC-MIN8</value>
            </entry>
            <entry name="UNLWEB">
              <value>UNLWEB</value>
            </entry>
            <entry name="RCSC-SEAT">
              <value>RCSC-SEAT</value>
            </entry>
            <entry name="RCEC-SEAT">
              <value>RCEC-SEAT</value>
            </entry>
            <entry name="EUROI">
              <value>EUROI</value>
            </entry>
            <entry name="PRC-1600">
              <value>PRC-1600</value>
            </entry>
            <entry name="PRC-1600R">
              <value>PRC-1600R</value>
            </entry>
            <entry name="PRC-2400">
              <value>PRC-2400</value>
            </entry>
            <entry name="PRC-2400R">
              <value>PRC-2400R</value>
            </entry>
            <entry name="PRC-400">
              <value>PRC-400</value>
            </entry>
            <entry name="PRC-400R">
              <value>PRC-400R</value>
            </entry>
            <entry name="PRC-800">
              <value>PRC-800</value>
            </entry>
            <entry name="PRC-800R">
              <value>PRC-800R</value>
            </entry>
            <entry name="RCEC-MICRO">
              <value>RCEC-MICRO</value>
            </entry>
            <entry name="RCEE-MICRO">
              <value>RCEE-MICRO</value>
            </entry>
            <entry name="RCTC-SEAT">
              <value>RCTC-SEAT</value>
            </entry>
            <entry name="VC-SEATSREG">
              <value>VC-SEATSREG</value>
            </entry>
            <entry name="EC-CD">
              <value>EC-CD</value>
            </entry>
            <entry name="EC-CONV">
              <value>EC-CONV</value>
            </entry>
            <entry name="EC-HOST">
              <value>EC-HOST</value>
            </entry>
            <entry name="EC-HOSTXL">
              <value>EC-HOSTXL</value>
            </entry>
            <entry name="VSD-90DA">
              <value>VSD-90DA</value>
            </entry>
            <entry name="VSD-AAH">
              <value>VSD-AAH</value>
            </entry>
            <entry name="VSD-AAS">
              <value>VSD-AAS</value>
            </entry>
            <entry name="VSD-ACIND">
              <value>VSD-ACIND</value>
            </entry>
            <entry name="VSD-ACPH">
              <value>VSD-ACPH</value>
            </entry>
            <entry name="VSD-ACPO">
              <value>VSD-ACPO</value>
            </entry>
            <entry name="VSD-ACQAP">
              <value>VSD-ACQAP</value>
            </entry>
            <entry name="VSD-ACSL">
              <value>VSD-ACSL</value>
            </entry>
            <entry name="VSD-AE">
              <value>VSD-AE</value>
            </entry>
            <entry name="VSD-AH">
              <value>VSD-AH</value>
            </entry>
            <entry name="VSD-AOD">
              <value>VSD-AOD</value>
            </entry>
            <entry name="VSD-AP">
              <value>VSD-AP</value>
            </entry>
            <entry name="VSD-CDA">
              <value>VSD-CDA</value>
            </entry>
            <entry name="VSD-CDB">
              <value>VSD-CDB</value>
            </entry>
            <entry name="VSD-CDF">
              <value>VSD-CDF</value>
            </entry>
            <entry name="VSD-CP">
              <value>VSD-CP</value>
            </entry>
            <entry name="VSD-H">
              <value>VSD-H</value>
            </entry>
            <entry name="VSD-LACL">
              <value>VSD-LACL</value>
            </entry>
            <entry name="VSD-LACS">
              <value>VSD-LACS</value>
            </entry>
            <entry name="VSD-LIL">
              <value>VSD-LIL</value>
            </entry>
            <entry name="VSD-LIS">
              <value>VSD-LIS</value>
            </entry>
            <entry name="VSD-LPU">
              <value>VSD-LPU</value>
            </entry>
            <entry name="VSD-PDFH">
              <value>VSD-PDFH</value>
            </entry>
            <entry name="VSD-PP">
              <value>VSD-PP</value>
            </entry>
            <entry name="VSD-REE">
              <value>VSD-REE</value>
            </entry>
            <entry name="VSD-RES">
              <value>VSD-RES</value>
            </entry>
            <entry name="VSD-SSP">
              <value>VSD-SSP</value>
            </entry>
            <entry name="VSD-SSRES">
              <value>VSD-SSRES</value>
            </entry>
            <entry name="VSD-STOR">
              <value>VSD-STOR</value>
            </entry>
            <entry name="VSD-TRAN">
              <value>VSD-TRAN</value>
            </entry>
            <entry name="VSD-URL">
              <value>VSD-URL</value>
            </entry>
            <entry name="QAP">
              <value>QAP</value>
            </entry>
            <entry name="ILWC-MIN">
              <value>ILWC-MIN</value>
            </entry>
            <entry name="ILWC-REC">
              <value>ILWC-REC</value>
            </entry>
            <entry name="COMB-MIN8">
              <value>COMB-MIN8</value>
            </entry>
            <entry name="COMB-MIND">
              <value>COMB-MIND</value>
            </entry>
            <entry name="CONF-MIN">
              <value>CONF-MIN</value>
            </entry>
            <entry name="PRC-295">
              <value>PRC-295</value>
            </entry>
            <entry name="PRC-295RR">
              <value>PRC-295RR</value>
            </entry>
            <entry name="PRC-295WR">
              <value>PRC-295WR</value>
            </entry>
            <entry name="PRC-295REF">
              <value>PRC-295REF</value>
            </entry>
          </entries>
        </enum>
        <enum name="FeatureUOM">
          <description>Unit of Measure for Features</description>
          <entries>
            <entry name="15 Minutes">
              <value>1/4</value>
              <value>1</value>
            </entry>
            <entry name="30 Minutes">
              <value>1/2</value>
              <value>2</value>
            </entry>
            <entry name="Minute">
              <value>MIN</value>
              <value>3</value>
            </entry>
            <entry name="Hour">
              <value>Hour</value>
              <value>4</value>
            </entry>
            <entry name="Day">
              <value>DAY</value>
              <value>5</value>
            </entry>
            <entry name="Each">
              <value>EA</value>
              <value>6</value>
            </entry>
            <entry name="Hit">
              <value>HIT</value>
              <value>7</value>
            </entry>
            <entry name="Page">
              <value>PAG</value>
              <value>8</value>
            </entry>
            <entry name="Sit">
              <value>SIT</value>
              <value>9</value>
            </entry>
          </entries>
        </enum>
      </enums>
    </enum_space>
  </enum_spaces>
</mt_enum_config>