<?xml version="1.0" encoding="UTF-8"?>
<mt_config>
    <language_code>es-mx</language_code>
    <locale_space name="metratech.com/audioconfFeature">
        <locale_entry>
            <Name>metratech.com/AudioConfFeature</Name>
            <Value>Función de conferencia de audio</Value>
        </locale_entry>
        <locale_entry>
            <Name>metratech.com/AudioConfFeature/Duration</Name>
            <Value>Duración</Value>
        </locale_entry>
        <locale_entry>
            <Name>metratech.com/AudioConfFeature/EndTime</Name>
            <Value>HoraFinalización</Value>
        </locale_entry>
        <locale_entry>
            <Name>metratech.com/AudioConfFeature/FeatureType</Name>
            <Value>Tipo de función</Value>
        </locale_entry>
        <locale_entry>
            <Name>metratech.com/audioconfFeature/FeatureType/PlaybackSetup</Name>
            <Value>Ajuste de sonido pregrabado</Value>
        </locale_entry>
        <locale_entry>
            <Name>metratech.com/audioconfFeature/FeatureType/Polling</Name>
            <Value>Encuesta</Value>
        </locale_entry>
        <locale_entry>
            <Name>metratech.com/audioconfFeature/FeatureType/QA</Name>
            <Value>P y R</Value>
        </locale_entry>
        <locale_entry>
            <Name>metratech.com/audioconfFeature/FeatureType/Record</Name>
            <Value>Registro</Value>
        </locale_entry>
        <locale_entry>
            <Name>metratech.com/audioconfFeature/FeatureType/TapesCopies</Name>
            <Value>Copias de cintas</Value>
        </locale_entry>
        <locale_entry>
            <Name>metratech.com/audioconfFeature/FeatureType/TapesOriginals</Name>
            <Value>Originales de cintas</Value>
        </locale_entry>
        <locale_entry>
            <Name>metratech.com/audioconfFeature/FeatureUOM/Days</Name>
            <Value>Días</Value>
        </locale_entry>
        <locale_entry>
            <Name>metratech.com/audioconfFeature/FeatureUOM/Hours</Name>
            <Value>Horas</Value>
        </locale_entry>
        <locale_entry>
            <Name>metratech.com/audioconfFeature/FeatureUOM/Minutes</Name>
            <Value>Minutos</Value>
        </locale_entry>
        <locale_entry>
            <Name>metratech.com/audioconfFeature/FeatureUOM/Seconds</Name>
            <Value>Segundos</Value>
        </locale_entry>
        <locale_entry>
            <Name>metratech.com/AudioConfFeature/GLCode</Name>
            <Value>CódigoGL</Value>
        </locale_entry>
        <locale_entry>
            <Name>metratech.com/AudioConfFeature/Metric</Name>
            <Value>Métrica</Value>
        </locale_entry>
        <locale_entry>
            <Name>metratech.com/AudioConfFeature/MetricCharge</Name>
            <Value>Cargo de función basado en métrica</Value>
        </locale_entry>
        <locale_entry>
            <Name>metratech.com/AudioConfFeature/Payer</Name>
            <Value>Pagador</Value>
        </locale_entry>
        <locale_entry>
            <Name>metratech.com/AudioConfFeature/RoundedDuration</Name>
            <Value>Duración aproximada</Value>
        </locale_entry>
        <locale_entry>
            <Name>metratech.com/AudioConfFeature/SetupCharge</Name>
            <Value>Cargo de ajuste</Value>
        </locale_entry>
        <locale_entry>
            <Name>metratech.com/AudioConfFeature/StartTime</Name>
            <Value>HoraInicio</Value>
        </locale_entry>
        <locale_entry>
            <Name>metratech.com/AudioConfFeature/TimeBasedCharge</Name>
            <Value>Cargo de función basado en hora</Value>
        </locale_entry>
        <locale_entry>
            <Name>metratech.com/AudioConfFeature/TransactionID</Name>
            <Value>ID de transacción</Value>
        </locale_entry>
    </locale_space>
</mt_config>