<?xml version="1.0" encoding="utf-8" ?> 
<MTConfig>

   <!-- MetraNet shortcut page configuration --> 
   <MetraNet>
      
      <!-- page title -->
      <Title>
        <![CDATA[
         MetraTech >>> Development Server >>> 6.7
        ]]>
      </Title>
      
      <Default>
        <!-- description of MetraNet server -->
        <MetraNetServerDescription>MetraNet Server 7.1.1</MetraNetServerDescription>
        
        <!-- type of server: DEMO, TEST, PRODUCTION, DEVELOPMENT -->
        <MetraNetServerType>[DEVELOPMENT]</MetraNetServerType>
      </Default>
      <de>
        <MetraNetServerDescription>MetraNet Server (DE)</MetraNetServerDescription>
        <MetraNetServerType>[DEVELOPMENT] (DE)</MetraNetServerType>
      </de>
      <fr>
        <MetraNetServerDescription>MetraNet Server (fr)</MetraNetServerDescription>
        <MetraNetServerType>[DEVELOPMENT] (fr)</MetraNetServerType>
      </fr>      
     
   </MetraNet>
  
</MTConfig>
