<?xml version="1.0" encoding="utf-8"?>
<EnumCategory xmlns:i="http://www.w3.org/2001/XMLSchema-instance" xmlns="MetraTech">
  <Description i:nil="true" />
  <Name>groupmethod</Name>
  <Values>
    <EnumValue>
      <Aliases xmlns:d4p1="http://schemas.microsoft.com/2003/10/Serialization/Arrays" />
      <Description i:nil="true" />
      <Name>folderpayee</Name>
    </EnumValue>
    <EnumValue>
      <Aliases xmlns:d4p1="http://schemas.microsoft.com/2003/10/Serialization/Arrays" />
      <Description i:nil="true" />
      <Name>folderpayer</Name>
    </EnumValue>
    <EnumValue>
      <Aliases xmlns:d4p1="http://schemas.microsoft.com/2003/10/Serialization/Arrays" />
      <Description i:nil="true" />
      <Name>payee</Name>
    </EnumValue>
    <EnumValue>
      <Aliases xmlns:d4p1="http://schemas.microsoft.com/2003/10/Serialization/Arrays" />
      <Description i:nil="true" />
      <Name>payer</Name>
    </EnumValue>
    <EnumValue>
      <Aliases xmlns:d4p1="http://schemas.microsoft.com/2003/10/Serialization/Arrays" />
      <Description i:nil="true" />
      <Name>subinvoice</Name>
    </EnumValue>
  </Values>
</EnumCategory>