<?xml version="1.0" encoding="utf-8"?>
<EnumCategory xmlns:i="http://www.w3.org/2001/XMLSchema-instance" xmlns="MetraTech">
  <Description i:nil="true" />
  <Name>error</Name>
  <Values>
    <EnumValue>
      <Aliases xmlns:d4p1="http://schemas.microsoft.com/2003/10/Serialization/Arrays" />
      <Description i:nil="true" />
      <Name>code</Name>
    </EnumValue>
    <EnumValue>
      <Aliases xmlns:d4p1="http://schemas.microsoft.com/2003/10/Serialization/Arrays" />
      <Description i:nil="true" />
      <Name>errormessage</Name>
    </EnumValue>
    <EnumValue>
      <Aliases xmlns:d4p1="http://schemas.microsoft.com/2003/10/Serialization/Arrays" />
      <Description i:nil="true" />
      <Name>failurecompoundid</Name>
    </EnumValue>
    <EnumValue>
      <Aliases xmlns:d4p1="http://schemas.microsoft.com/2003/10/Serialization/Arrays" />
      <Description i:nil="true" />
      <Name>failureid</Name>
    </EnumValue>
    <EnumValue>
      <Aliases xmlns:d4p1="http://schemas.microsoft.com/2003/10/Serialization/Arrays" />
      <Description i:nil="true" />
      <Name>failureservicename</Name>
    </EnumValue>
    <EnumValue>
      <Aliases xmlns:d4p1="http://schemas.microsoft.com/2003/10/Serialization/Arrays" />
      <Description i:nil="true" />
      <Name>failuretime</Name>
    </EnumValue>
    <EnumValue>
      <Aliases xmlns:d4p1="http://schemas.microsoft.com/2003/10/Serialization/Arrays" />
      <Description i:nil="true" />
      <Name>line</Name>
    </EnumValue>
    <EnumValue>
      <Aliases xmlns:d4p1="http://schemas.microsoft.com/2003/10/Serialization/Arrays" />
      <Description i:nil="true" />
      <Name>meteredtime</Name>
    </EnumValue>
    <EnumValue>
      <Aliases xmlns:d4p1="http://schemas.microsoft.com/2003/10/Serialization/Arrays" />
      <Description i:nil="true" />
      <Name>method</Name>
    </EnumValue>
    <EnumValue>
      <Aliases xmlns:d4p1="http://schemas.microsoft.com/2003/10/Serialization/Arrays" />
      <Description i:nil="true" />
      <Name>module</Name>
    </EnumValue>
    <EnumValue>
      <Aliases xmlns:d4p1="http://schemas.microsoft.com/2003/10/Serialization/Arrays" />
      <Description i:nil="true" />
      <Name>plugin</Name>
    </EnumValue>
    <EnumValue>
      <Aliases xmlns:d4p1="http://schemas.microsoft.com/2003/10/Serialization/Arrays" />
      <Description i:nil="true" />
      <Name>possibleaccountid</Name>
    </EnumValue>
    <EnumValue>
      <Aliases xmlns:d4p1="http://schemas.microsoft.com/2003/10/Serialization/Arrays" />
      <Description i:nil="true" />
      <Name>sender</Name>
    </EnumValue>
    <EnumValue>
      <Aliases xmlns:d4p1="http://schemas.microsoft.com/2003/10/Serialization/Arrays" />
      <Description i:nil="true" />
      <Name>stagename</Name>
    </EnumValue>
    <EnumValue>
      <Aliases xmlns:d4p1="http://schemas.microsoft.com/2003/10/Serialization/Arrays" />
      <Description i:nil="true" />
      <Name>state</Name>
    </EnumValue>
    <EnumValue>
      <Aliases xmlns:d4p1="http://schemas.microsoft.com/2003/10/Serialization/Arrays" />
      <Description i:nil="true" />
      <Name>tx_batch</Name>
    </EnumValue>
  </Values>
</EnumCategory>