<?xml version="1.0" encoding="UTF-8"?>
<mt_config>
    <language_code>en-GB</language_code>
    <locale_space name="metratech.com/Events">
        <locale_entry>
            <Name>metratech.com/Events/Action/Execute</Name>
            <Value>[en-GB] Execute</Value>
        </locale_entry>
        <locale_entry>
            <Name>metratech.com/Events/Action/Reverse</Name>
            <Value>[en-GB] Reverse </Value>
        </locale_entry>
        <locale_entry>
            <Name>metratech.com/Events/Status/Failed</Name>
            <Value>[en-GB] Failed</Value>
        </locale_entry>
        <locale_entry>
            <Name>metratech.com/Events/Status/NotYetRun</Name>
            <Value>[en-GB] NotYetRun</Value>
        </locale_entry>
        <locale_entry>
            <Name>metratech.com/Events/Status/ReadyToRun</Name>
            <Value>[en-GB] ReadyToRun</Value>
        </locale_entry>
        <locale_entry>
            <Name>metratech.com/Events/Status/Succeeded</Name>
            <Value>[en-GB] Succeeded</Value>
        </locale_entry>
    </locale_space>
</mt_config>