<?xml version="1.0" encoding="utf-8"?>
<PageLayout>
    <Name>DataExportFramework.QueueAdhocReports</Name>
    <AssemblyName>MetraTech.DomainModel.Billing.dll</AssemblyName>
    <ObjectName>MetraTech.DomainModel.Billing.ExportReportDefinition</ObjectName>
    <Description>This feature lets you initiate a report at any time regardless of report schedule. It's useful to test new report definitions, before you define report instances.</Description>
    <Pages>
        <PageName>~/DataExportReportManagement/QueueAdHocReports.aspx</PageName>
    </Pages>
    <Header>
        <PageTitle>
            <Value><![CDATA[]]></Value>
        </PageTitle>
    </Header>
    <Help>
        <Mode>None</Mode>
        <Name></Name>
        <URL></URL>
    </Help>
    <Sections>
        <Section>
            <Title>
                <LocalizationTag>TEXT_QUEUSE_ADHOC_REPORTS</LocalizationTag>
                <ResourceClassKey>DataExportReportManagement/App_LocalResources/QueueAdHocReports.aspx</ResourceClassKey>
            </Title>
            <TabOrder>LeftToRight</TabOrder>
            <Name></Name>
            <Columns>
                <Column>
                    <Fields>
                        <Field>
                            <AssemblyFilename>MetraTech.DomainModel.Billing.dll</AssemblyFilename>
                            <ObjectName>MetraTech.DomainModel.Billing.ExportReportDefinition</ObjectName>
                            <ID>AdhocReportOutputType</ID>
                            <Name>AdhocReportOutputType</Name>
                            <Alignment>Left</Alignment>
                            <ReadOnly>false</ReadOnly>
                            <ControlType>MetraTech.UI.Controls.MTDropDown</ControlType>
                            <IgnoreIceValidation>False</IgnoreIceValidation>
                            <EditorValidation>
                                <Required>false</Required>
                                <ValidationType></ValidationType>
                            </EditorValidation>
                            <OptionalExtConfig>width:90,height:60,</OptionalExtConfig>
                            <Label>
                                <LocalizationTag>TEXT_DEF_REPORT_OUTPUT_TYPE</LocalizationTag>
                                <ResourceClassKey>DataExportReportManagement/App_LocalResources/QueueAdHocReports.aspx</ResourceClassKey>
                            </Label>
                            <RequiredCapabilities />
                            <RequiredCapabilitiesReadonly />
                        </Field>
                        <Field>
                            <AssemblyFilename>MetraTech.DomainModel.Billing.dll</AssemblyFilename>
                            <ObjectName>MetraTech.DomainModel.Billing.ExportReportDefinition</ObjectName>
                            <ID>AdhocOutputFileName</ID>
                            <Name>AdhocOutputFileName</Name>
                            <Alignment>Left</Alignment>
                            <ReadOnly>false</ReadOnly>
                            <ControlType>MetraTech.UI.Controls.MTTextBox</ControlType>
                            <IgnoreIceValidation>False</IgnoreIceValidation>
                            <EditorValidation>
                                <Required>true</Required>
                                <ValidationType></ValidationType>
                            </EditorValidation>
                            <OptionalExtConfig></OptionalExtConfig>
                            <Label>
                                <LocalizationTag>TEXT_DEF_REPORT_OUTPUT_FILE_NAME</LocalizationTag>
                                <ResourceClassKey>DataExportReportManagement/App_LocalResources/QueueAdHocReports.aspx</ResourceClassKey>
                            </Label>
                            <RequiredCapabilities />
                            <RequiredCapabilitiesReadonly />
                        </Field>
                        <Field>
                            <AssemblyFilename>MetraTech.DomainModel.Billing.dll</AssemblyFilename>
                            <ObjectName>MetraTech.DomainModel.Billing.ExportReportDefinition</ObjectName>
                            <ID>bAdhocOutputExecParameters</ID>
                            <Name>bAdhocOutputExecParameters</Name>
                            <Alignment>Left</Alignment>
                            <ReadOnly>false</ReadOnly>
                            <ControlType>MetraTech.UI.Controls.MTCheckBox</ControlType>
                            <IgnoreIceValidation>False</IgnoreIceValidation>
                            <EditorValidation>
                                <Required>false</Required>
                                <ValidationType></ValidationType>
                            </EditorValidation>
                            <OptionalExtConfig></OptionalExtConfig>
                            <Label>
                                <LocalizationTag>TEXT_DEF_OUTPUT_EXEC_PARAMETERS</LocalizationTag>
                                <ResourceClassKey>DataExportReportManagement/App_LocalResources/QueueAdHocReports.aspx</ResourceClassKey>
                            </Label>
                            <RequiredCapabilities />
                            <RequiredCapabilitiesReadonly />
                        </Field>
                    </Fields>
                </Column>
                <Column>
                    <Fields>
                        <Field>
                            <AssemblyFilename>MetraTech.DomainModel.Billing.dll</AssemblyFilename>
                            <ObjectName>MetraTech.DomainModel.Billing.ExportReportDefinition</ObjectName>
                            <ID>bAdhocCompressReport</ID>
                            <Name>bAdhocCompressReport</Name>
                            <Alignment>Left</Alignment>
                            <ReadOnly>false</ReadOnly>
                            <ControlType>MetraTech.UI.Controls.MTCheckBox</ControlType>
                            <IgnoreIceValidation>False</IgnoreIceValidation>
                            <EditorValidation>
                                <Required>false</Required>
                                <ValidationType></ValidationType>
                            </EditorValidation>
                            <OptionalExtConfig></OptionalExtConfig>
                            <Label>
                                <LocalizationTag>TEXT_DEF_COMPRESS_OUTPUT_FILE</LocalizationTag>
                                <ResourceClassKey>DataExportReportManagement/App_LocalResources/QueueAdHocReports.aspx</ResourceClassKey>
                            </Label>
                            <RequiredCapabilities />
                            <RequiredCapabilitiesReadonly />
                        </Field>
                        <Field>
                            <AssemblyFilename>MetraTech.DomainModel.Billing.dll</AssemblyFilename>
                            <ObjectName>MetraTech.DomainModel.Billing.ExportReportDefinition</ObjectName>
                            <ID>AdhocCompressThreshold</ID>
                            <Name>AdhocCompressThreshold</Name>
                            <Alignment>Left</Alignment>
                            <ReadOnly>false</ReadOnly>
                            <ControlType>MetraTech.UI.Controls.MTTextBox</ControlType>
                            <IgnoreIceValidation>False</IgnoreIceValidation>
                            <EditorValidation>
                                <Required>false</Required>
                                <ValidationType></ValidationType>
                            </EditorValidation>
                            <OptionalExtConfig></OptionalExtConfig>
                            <Label>
                                <LocalizationTag>TEXT_DEF_COMPRESS_THRESHOLD</LocalizationTag>
                                <ResourceClassKey>DataExportReportManagement/App_LocalResources/QueueAdHocReports.aspx</ResourceClassKey>
                            </Label>
                            <RequiredCapabilities />
                            <RequiredCapabilitiesReadonly />
                        </Field>
                        <Field>
                            <AssemblyFilename>MetraTech.DomainModel.Billing.dll</AssemblyFilename>
                            <ObjectName>MetraTech.DomainModel.Billing.ExportReportDefinition</ObjectName>
                            <ID>bAdhocUseQuotedIdentifiers</ID>
                            <Name>bAdhocUseQuotedIdentifiers</Name>
                            <Alignment>Left</Alignment>
                            <ReadOnly>false</ReadOnly>
                            <ControlType>MetraTech.UI.Controls.MTCheckBox</ControlType>
                            <IgnoreIceValidation>False</IgnoreIceValidation>
                            <EditorValidation>
                                <Required>false</Required>
                                <ValidationType></ValidationType>
                            </EditorValidation>
                            <OptionalExtConfig></OptionalExtConfig>
                            <Label>
                                <LocalizationTag>TEXT_DEF_USE_QUOTED_IDENTIFIERS</LocalizationTag>
                                <ResourceClassKey>DataExportReportManagement/App_LocalResources/QueueAdHocReports.aspx</ResourceClassKey>
                            </Label>
                            <RequiredCapabilities />
                            <RequiredCapabilitiesReadonly />
                        </Field>
                    </Fields>
                </Column>
            </Columns>
            <ToolbarButtons></ToolbarButtons>
        </Section>
    </Sections>
</PageLayout>