<priceable_item><name>MovieTickets</name><description>Online movie ticket purchases</description><item_type>aggregate</item_type><relationships><parent></parent></relationships><parameter_table>ticketprices</parameter_table><parameter_table>popcornprices</parameter_table><counters><cpd><name>TotalTickets</name><display_name>total tickets purchased</display_name><service_property>TotalTickets</service_property><preferred_counter_type>SumOfOneProperty</preferred_counter_type></cpd><cpd><name>TotalPopcorns</name><display_name>total bags of popcorn</display_name><service_property>TotalPopcorns</service_property><preferred_counter_type>SumOfOneProperty</preferred_counter_type></cpd><counter><name>TotalTickets</name><type>SumOfOneProperty</type><parameter><name>A</name><product_view>metratech.com/movietickets_temp</product_view><value>metratech.com/movietickets_temp/ticketspurchased</value><kind>ProductViewProperty</kind></parameter></counter><counter><name>TotalPopcorns</name><type>SumOfOneProperty</type><parameter><name>A</name><product_view>metratech.com/movietickets_temp</product_view><value>metratech.com/movietickets_temp/popcorns</value><kind>ProductViewProperty</kind></parameter></counter></counters><pipeline><service_definition>metratech.com/movietickets</service_definition><product_view>metratech.com/movietickets</product_view></pipeline></priceable_item>
