<?xml version="1.0" encoding="utf-8"?>
<Query>
    <Action>CreateDatabase</Action>
    <Implementations>
        <Implementation>SqlServer</Implementation>
        <Implementation>Oracle</Implementation>
    </Implementations>
    <Schemas>
        <Schema>NetMeter</Schema>
        <Schema>Staging</Schema>
    </Schemas>
    <InstallTime>PreSync</InstallTime>
    <Parameters>
        <Parameter>
            <Name>DATABASE_NAME</Name>
            <DataType>unknown</DataType>
            <ReplacementType>DoublePercent</ReplacementType>
            <Description></Description>
        </Parameter>
        <Parameter>
            <Name>DATA_DEVICE_NAME</Name>
            <DataType>string</DataType>
            <ReplacementType>DoublePercent</ReplacementType>
            <Description></Description>
        </Parameter>
        <Parameter>
            <Name>DATA_DEVICE_LOCATION</Name>
            <DataType>string</DataType>
            <ReplacementType>DoublePercent</ReplacementType>
            <Description></Description>
        </Parameter>
        <Parameter>
            <Name>DATA_DEVICE_SIZE</Name>
            <DataType>unknown</DataType>
            <ReplacementType>DoublePercent</ReplacementType>
            <Description></Description>
        </Parameter>
        <Parameter>
            <Name>LOG_DEVICE_NAME</Name>
            <DataType>string</DataType>
            <ReplacementType>DoublePercent</ReplacementType>
            <Description></Description>
        </Parameter>
        <Parameter>
            <Name>LOG_DEVICE_LOCATION</Name>
            <DataType>string</DataType>
            <ReplacementType>DoublePercent</ReplacementType>
            <Description></Description>
        </Parameter>
        <Parameter>
            <Name>LOG_DEVICE_SIZE</Name>
            <DataType>unknown</DataType>
            <ReplacementType>DoublePercent</ReplacementType>
            <Description></Description>
        </Parameter>
    </Parameters>
    <Description></Description>
    <ConversionAudit>
        <ConversionDuplicateName></ConversionDuplicateName>
        <CommonQuerySourceFile></CommonQuerySourceFile>
        <SqlServerQuerySourceFile>R:\Config\Queries\DBInstall\Queries.xml</SqlServerQuerySourceFile>
        <OracleQuerySourceFile>R:\Config\Queries\DBInstall\Queries_Oracle.xml</OracleQuerySourceFile>
    </ConversionAudit>
</Query>
